junbedded/__init__.py
junbedded/ip_controll.py
junbedded-0.0.1.dist-info/METADATA
junbedded-0.0.1.dist-info/WHEEL
junbedded-0.0.1.dist-info/top_level.txt
junbedded-0.0.1.dist-info/RECORD
