Metadata-Version: 2.4
Name: junbedded
Version: 0.0.1
Summary: Python Embedded Personal Tools
Home-page: https://github.com/wnsdlf925/junbedded.git
Author: wnsdlf925
Author-email: wnsdlf925@naver.com
Keywords: junbedded,wnsdlf925,python,rasberry pi
Classifier: Programming Language :: Python :: 3.9
Classifier: Programming Language :: Python :: 3.10
Classifier: Programming Language :: Python :: 3.11
Classifier: Programming Language :: Python :: 3.12
Requires-Python: >=3.9
Dynamic: author
Dynamic: author-email
Dynamic: classifier
Dynamic: home-page
Dynamic: keywords
Dynamic: requires-python
Dynamic: summary
